slidown/__init__.py
slidown/__version__.py
slidown/config.py
slidown/core.py
slidown/file_utils.py
slidown/gui.py
slidown/main.py
slidown/monitor.py
slidown/reveal.js/LICENSE
slidown/reveal.js/README.md
slidown/reveal.js/demo.html
slidown/reveal.js/gulpfile.js
slidown/reveal.js/index.html
slidown/reveal.js/package-lock.json
slidown/reveal.js/package.json
slidown/reveal.js/css/layout.scss
slidown/reveal.js/css/reveal.scss
slidown/reveal.js/css/print/paper.scss
slidown/reveal.js/css/print/pdf.scss
slidown/reveal.js/css/theme/README.md
slidown/reveal.js/css/theme/source/beige.scss
slidown/reveal.js/css/theme/source/black-contrast.scss
slidown/reveal.js/css/theme/source/black.scss
slidown/reveal.js/css/theme/source/blood.scss
slidown/reveal.js/css/theme/source/dracula.scss
slidown/reveal.js/css/theme/source/league.scss
slidown/reveal.js/css/theme/source/moon.scss
slidown/reveal.js/css/theme/source/night.scss
slidown/reveal.js/css/theme/source/serif.scss
slidown/reveal.js/css/theme/source/simple.scss
slidown/reveal.js/css/theme/source/sky.scss
slidown/reveal.js/css/theme/source/solarized.scss
slidown/reveal.js/css/theme/source/white-contrast.scss
slidown/reveal.js/css/theme/source/white.scss
slidown/reveal.js/css/theme/template/exposer.scss
slidown/reveal.js/css/theme/template/mixins.scss
slidown/reveal.js/css/theme/template/settings.scss
slidown/reveal.js/css/theme/template/theme.scss
slidown/reveal.js/dist/reset.css
slidown/reveal.js/dist/reveal.css
slidown/reveal.js/dist/reveal.esm.js
slidown/reveal.js/dist/reveal.esm.js.map
slidown/reveal.js/dist/reveal.js
slidown/reveal.js/dist/reveal.js.map
slidown/reveal.js/dist/theme/beige.css
slidown/reveal.js/dist/theme/black-contrast.css
slidown/reveal.js/dist/theme/black.css
slidown/reveal.js/dist/theme/blood.css
slidown/reveal.js/dist/theme/dracula.css
slidown/reveal.js/dist/theme/league.css
slidown/reveal.js/dist/theme/moon.css
slidown/reveal.js/dist/theme/night.css
slidown/reveal.js/dist/theme/serif.css
slidown-2.dist-info/METADATA
slidown-2.dist-info/WHEEL
slidown-2.dist-info/entry_points.txt
slidown-2.dist-info/top_level.txt
slidown-2.dist-info/RECORD
