Metadata-Version: 2.4
Name: slidown
Version: 2
Summary: A Deckset-like presentation tool using reveal.js and Pandoc
Author-email: Riccardo Marotti <slidown@ric.mozmail.com>
Maintainer-email: Riccardo Marotti <slidown@ric.mozmail.com>
License-Expression: GPL-3.0-only
Project-URL: Homepage, https://github.com/riccardomarotti/slidown
Project-URL: Repository, https://github.com/riccardomarotti/slidown
Project-URL: Bug Tracker, https://github.com/riccardomarotti/slidown/issues
Keywords: presentation,markdown,reveal.js,pandoc,slides
Classifier: Development Status :: 4 - Beta
Classifier: Environment :: X11 Applications :: Qt
Classifier: Intended Audience :: End Users/Desktop
Classifier: Operating System :: OS Independent
Classifier: Programming Language :: Python :: 3
Classifier: Programming Language :: Python :: 3.8
Classifier: Programming Language :: Python :: 3.9
Classifier: Programming Language :: Python :: 3.10
Classifier: Programming Language :: Python :: 3.11
Classifier: Programming Language :: Python :: 3.12
Classifier: Topic :: Multimedia :: Graphics :: Presentation
Classifier: Topic :: Office/Business
Classifier: Topic :: Text Processing :: Markup :: HTML
Requires-Python: >=3.8
Requires-Dist: pypandoc
Requires-Dist: beautifulsoup4
Requires-Dist: appdirs
Requires-Dist: PyQt5
Requires-Dist: PyQtWebEngine
Provides-Extra: dev
Requires-Dist: pytest; extra == "dev"
Requires-Dist: pytest-cov>=2.5.1; extra == "dev"
Requires-Dist: python-coveralls; extra == "dev"
Requires-Dist: pyinstaller; extra == "dev"
